helloensai/__main__.py
helloensai-0.1.1.dist-info/METADATA
helloensai-0.1.1.dist-info/WHEEL
helloensai-0.1.1.dist-info/RECORD
