Metadata-Version: 2.1
Name: helloensai
Version: 0.1.1
Summary: Projet helloensai pour exemple de publication de livrable sur pypi
License: MIT
Author: Antoine Brunetti
Requires-Python: >=3.10,<4.0
Classifier: License :: OSI Approved :: MIT License
Classifier: Programming Language :: Python :: 3
Classifier: Programming Language :: Python :: 3.10
Classifier: Programming Language :: Python :: 3.11
Classifier: Programming Language :: Python :: 3.12
Classifier: Programming Language :: Python :: 3.13
